setup.py
restapi/__init__.py
restapi/application.py
restapi/daemon.py
restapi/exceptions.py
restapi/interfaces.py
restapi/main.py
restapi/middlewares.py
restapi/requests.py
restapi/responses.py
restapi/serializers.py
restapi/utils.py
restapi/version.py
restapi2.egg-info/PKG-INFO
restapi2.egg-info/SOURCES.txt
restapi2.egg-info/dependency_links.txt
restapi2.egg-info/requires.txt
restapi2.egg-info/top_level.txt